pycadf/__init__.py
pycadf/attachment.py
pycadf/cadftaxonomy.py
pycadf/cadftype.py
pycadf/credential.py
pycadf/endpoint.py
pycadf/event.py
pycadf/eventfactory.py
pycadf/geolocation.py
pycadf/host.py
pycadf/identifier.py
pycadf/measurement.py
pycadf/metric.py
pycadf/path.py
pycadf/reason.py
pycadf/reporterstep.py
pycadf/resource.py
pycadf/tag.py
pycadf/timestamp.py
pycadf/utils.py
pycadf/helper/__init__.py
pycadf/helper/api.py
pycadf/tests/__init__.py
pycadf/tests/base.py
pycadf/tests/test_cadf_spec.py
pycadf/tests/test_utils.py
pycadf/tests/helper/__init__.py
pycadf/tests/helper/test_api.py
pycadf-4.0.1.data/data/etc/pycadf/cinder_api_audit_map.conf
pycadf-4.0.1.data/data/etc/pycadf/glance_api_audit_map.conf
pycadf-4.0.1.data/data/etc/pycadf/gnocchi_api_audit_map.conf
pycadf-4.0.1.data/data/etc/pycadf/heat_api_audit_map.conf
pycadf-4.0.1.data/data/etc/pycadf/ironic_api_audit_map.conf
pycadf-4.0.1.data/data/etc/pycadf/neutron_api_audit_map.conf
pycadf-4.0.1.data/data/etc/pycadf/nova_api_audit_map.conf
pycadf-4.0.1.data/data/etc/pycadf/swift_api_audit_map.conf
pycadf-4.0.1.data/data/etc/pycadf/trove_api_audit_map.conf
pycadf-4.0.1.dist-info/AUTHORS
pycadf-4.0.1.dist-info/LICENSE
pycadf-4.0.1.dist-info/METADATA
pycadf-4.0.1.dist-info/WHEEL
pycadf-4.0.1.dist-info/pbr.json
pycadf-4.0.1.dist-info/top_level.txt
pycadf-4.0.1.dist-info/RECORD
